test2022/__init__.py
test2022-0.1.dist-info/DESCRIPTION.rst
test2022-0.1.dist-info/METADATA
test2022-0.1.dist-info/RECORD
test2022-0.1.dist-info/WHEEL
test2022-0.1.dist-info/metadata.json
test2022-0.1.dist-info/top_level.txt
