Metadata-Version: 2.0
Name: test2022
Version: 0.1
Summary: Testing something
Home-page: UNKNOWN
Author: Tector Pro
Author-email: UNKNOWN
License: UNKNOWN
Platform: UNKNOWN
